IMPACT/__init__.py
IMPACT/dataset/__init__.py
IMPACT/dataset/dataset.py
IMPACT/model/IMPACT.py
IMPACT/model/__init__.py
IMPACT/model/abstract_model.py
IMPACT/utils/__init__.py
IMPACT/utils/utils.py
experiments/__init__.py
experiments/datasets/__init__.py
experiments/datasets/data_utils/DeepMTP_util.py
experiments/datasets/data_utils/__init__.py
experiments/datasets/data_utils/preprocessing_utilities.py
experiments/datasets/external_packages/__init__.py
experiments/datasets/external_packages/bivae.py
experiments/datasets/external_packages/cornac_util.py
experiments/datasets/external_packages/exception.py
experiments/datasets/external_packages/recom_bivaecf.py
experiments/datasets/external_packages/recommender.py
lirisimpact-2.0.25.dist-info/LICENSE
lirisimpact-2.0.25.dist-info/METADATA
lirisimpact-2.0.25.dist-info/WHEEL
lirisimpact-2.0.25.dist-info/top_level.txt
lirisimpact-2.0.25.dist-info/RECORD
